livefs_edit/__init__.py
livefs_edit/__main__.py
livefs_edit/actions.py
livefs_edit/cli.py
livefs_edit/context.py
livefs_edit-0.0.4.dist-info/METADATA
livefs_edit-0.0.4.dist-info/WHEEL
livefs_edit-0.0.4.dist-info/entry_points.txt
livefs_edit-0.0.4.dist-info/top_level.txt
livefs_edit-0.0.4.dist-info/RECORD
