Metadata-Version: 2.1
Name: livefs-edit
Version: 0.0.4
Summary: Tools for modifying Ubuntu Live ISOs
Home-page: https://github.com/mwhudson/livefs-edit
Author: Michael Hudson-Doyle
Author-email: michael.hudson@ubuntu.com
License: UNKNOWN
Project-URL: Bug Tracker, https://github.com/mwhudson/livefs-edit/issues
Platform: UNKNOWN
Classifier: Programming Language :: Python :: 3
Classifier: Operating System :: POSIX :: Linux
Requires-Python: >=3.6
